<annotation><folder>train</folder><filename>12.JPG</filename><path>/root/Work/ODDP/app/resource/task/5eca6c894238091e8b12a69d/images/train/12.JPG</path><source><database>Unknown</database></source><size><width>800</width><height>600</height><depth>3</depth></size><segmented>0</segmented><object><name>5eca67a90202601e8cb8d104</name><pose>Unspecified</pose><truncated>0</truncated><difficult>0</difficult><bndbox><xmin>122</xmin><ymin>249</ymin><xmax>700</xmax><ymax>409</ymax></bndbox></object></annotation>
